pdftools/__init__.py
pdftools/_version.py
pdftools/parseutil.py
pdftools/pdftools.py
pdftools-1.1.1.data/scripts/pdfadd.py
pdftools-1.1.1.data/scripts/pdfcopy.py
pdftools-1.1.1.data/scripts/pdfinsert.py
pdftools-1.1.1.data/scripts/pdfmerge.py
pdftools-1.1.1.data/scripts/pdfremove.py
pdftools-1.1.1.data/scripts/pdfrotate.py
pdftools-1.1.1.data/scripts/pdfsplit.py
pdftools-1.1.1.data/scripts/pdfzip.py
pdftools-1.1.1.dist-info/DESCRIPTION.rst
pdftools-1.1.1.dist-info/METADATA
pdftools-1.1.1.dist-info/RECORD
pdftools-1.1.1.dist-info/WHEEL
pdftools-1.1.1.dist-info/metadata.json
pdftools-1.1.1.dist-info/top_level.txt
