Metadata-Version: 2.0
Name: pdftools
Version: 1.1.1
Summary: A collection of convenience scripts for pdf manipulation, based on the PyPdf2 package.
Home-page: https://github.com/MrLeeh/pdftools
Author: Stefan Lehmann
Author-email: Stefan.St.Lehmann@gmail.com
License: MIT
Platform: UNKNOWN
Requires-Dist: PyPdf2
